[{"endpoint":"twitter/tweets","recordId":"1ad07eda-7d3e-4f2f-b9ec-721b45303317","data":{"id":404242507258925060,"geo":null,"lang":"und","text":"@MichaelEDyson @mtloveland","user":{"id":2167480290,"url":null,"lang":null,"name":"Julian Hamm","id_str":"2167480290","entities":{"description":{"urls":[]}},"location":"","verified":false,"following":false,"protected":false,"time_zone":null,"created_at":"Fri Nov 01 00:30:18 +0000 2013","utc_offset":null,"description":"","geo_enabled":false,"screen_name":"HonJHamm","listed_count":0,"friends_count":0,"is_translator":false,"notifications":false,"statuses_count":1,"default_profile":true,"followers_count":3,"translator_type":"none","favourites_count":2,"profile_image_url":"http://pbs.twimg.com/profile_images/378800000778819622/7d61e31ec82a0f04cc15b8dd57d77d7a_normal.jpeg","profile_banner_url":"https://pbs.twimg.com/profile_banners/2167480290/1383266181","profile_link_color":"1DA1F2","profile_text_color":"333333","follow_request_sent":false,"contributors_enabled":false,"has_extended_profile":false,"default_profile_image":false,"is_translation_enabled":false,"profile_background_tile":false,"profile_image_url_https":"https://pbs.twimg.com/profile_images/378800000778819622/7d61e31ec82a0f04cc15b8dd57d77d7a_normal.jpeg","profile_background_color":"C0DEED","profile_sidebar_fill_color":"DDEEF6","profile_background_image_url":"http://abs.twimg.com/images/themes/theme1/bg.png","profile_sidebar_border_color":"C0DEED","profile_use_background_image":true,"profile_background_image_url_https":"https://abs.twimg.com/images/themes/theme1/bg.png"},"place":null,"id_str":"404242507258925056","source":"<a href=\"http://twitter.com/download/android\" rel=\"nofollow\">Twitter for Android</a>","entities":{"urls":[],"symbols":[],"hashtags":[],"user_mentions":[{"id":55334133,"name":"Michael Eric Dyson","id_str":"55334133","indices":[0,14],"screen_name":"MichaelEDyson"},{"id":515887973,"name":"matt loveland","id_str":"515887973","indices":[15,26],"screen_name":"mtloveland"}]},"favorited":true,"retweeted":false,"truncated":false,"created_at":"Sat Nov 23 13:38:18 +0000 2013","coordinates":null,"lastUpdated":"2013-11-23T13:38:18.000Z","contributors":null,"retweet_count":1,"favorite_count":2,"is_quote_status":false,"in_reply_to_user_id":55334133,"in_reply_to_status_id":404166257106509800,"in_reply_to_screen_name":"MichaelEDyson","in_reply_to_user_id_str":"55334133","in_reply_to_status_id_str":"404166257106509824"}}]
